yqdata/__init__.py
yqdata/__main__.py
yqdata/services/__init__.py
yqdata/services/basic.py
yqdata/services/common.py
yqdata/services/concept.py
yqdata/services/factor.py
yqdata/services/stock.py
yqdata/utils/__init__.py
yqdata/utils/opensearch.py
yqdata-1.4.2.dist-info/LICENSE
yqdata-1.4.2.dist-info/METADATA
yqdata-1.4.2.dist-info/WHEEL
yqdata-1.4.2.dist-info/entry_points.txt
yqdata-1.4.2.dist-info/top_level.txt
yqdata-1.4.2.dist-info/RECORD
